scripts/__init__.py
scripts/server.py
scripts/server_simple.py
scripts/sirene.py
insee_mcp-0.1.12.dist-info/METADATA
insee_mcp-0.1.12.dist-info/WHEEL
insee_mcp-0.1.12.dist-info/entry_points.txt
insee_mcp-0.1.12.dist-info/top_level.txt
insee_mcp-0.1.12.dist-info/RECORD
