Metadata-Version: 2.4
Name: insee-mcp
Version: 0.1.12
Summary: Serveur MCP pour accéder aux données INSEE (SIRENE, BDM, Nomenclatures)
Author-email: Kerryan <kerryan.mace@student-cs.fr>
Project-URL: Homepage, https://github.com/KerryanOPMace/mcp-insee
Project-URL: Repository, https://github.com/KerryanOPMace/mcp-insee
Project-URL: Issues, https://github.com/KerryanOPMace/mcp-insee/issues
Requires-Python: >=3.10
Requires-Dist: fastmcp
Requires-Dist: pynsee
Requires-Dist: rapidfuzz
Requires-Dist: setuptools
